pynotes2/__init__.py
pynotes2/__main__.py
pynotes2/old_main
pynotes2-0.1.1.dist-info/entry_points.txt
pynotes2-0.1.1.dist-info/LICENSE
pynotes2-0.1.1.dist-info/WHEEL
pynotes2-0.1.1.dist-info/METADATA
pynotes2-0.1.1.dist-info/RECORD
